composex/__init__.py
composex/cli.py
composex/composex.py
composex-0.0.1.dist-info/AUTHORS.rst
composex-0.0.1.dist-info/LICENSE
composex-0.0.1.dist-info/METADATA
composex-0.0.1.dist-info/WHEEL
composex-0.0.1.dist-info/entry_points.txt
composex-0.0.1.dist-info/top_level.txt
composex-0.0.1.dist-info/RECORD
